RADX/__init__.py
RADX/disk_plot.py
RADX/functions.py
RADX/radx_functions.py
RADX-0.0.3.dist-info/METADATA
RADX-0.0.3.dist-info/WHEEL
RADX-0.0.3.dist-info/top_level.txt
RADX-0.0.3.dist-info/RECORD
