Metadata-Version: 2.1
Name: RADX
Version: 0.0.3
Requires-Dist: numpy
